README.rst
setup.py
appinstance/__init__.py
appinstance.egg-info/PKG-INFO
appinstance.egg-info/SOURCES.txt
appinstance.egg-info/dependency_links.txt
appinstance.egg-info/top_level.txt
appinstance.egg-info/zip-safe