Metadata-Version: 1.1
Name: appinstance
Version: 26
Summary: Check if an app with the same name is running, supports parameters.
Home-page: https://github.com/erikdejonge/appinstance
Author: Erik de Jonge
Author-email: erik@a8.nl
License: GPL
Platform: UNKNOWN
Classifier: Programming Language :: Python
Classifier: Programming Language :: Python :: 3
Classifier: Development Status :: 4 - Beta 
Classifier: Intended Audience :: Developers
Classifier: License :: OSI Approved :: GNU Library or Lesser General Public License (LGPL)
Classifier: Operating System :: POSIX
Classifier: Topic :: Software Development :: Libraries :: Python Modules
Classifier: Topic :: System
Requires: netifaces
Requires: future
Requires: pygments
